MANIFEST.in
res_config_view.xml
setup.py
./__init__.py
./__openerp__.py
./res_config.py
./test_easyftp.py
./ftpserver/__init__.py
./ftpserver/abstracted_fs.py
./ftpserver/authorizer.py
./ftpserver/ftpserver.py
./wizard/__init__.py
./wizard/ftp_browse.py
./wizard/ftp_configuration.py
i18n/ar.po
i18n/bg.po
i18n/ca.po
i18n/cs.po
i18n/da.po
i18n/de.po
i18n/document_ftp.pot
i18n/el.po
i18n/en_GB.po
i18n/es.po
i18n/es_CR.po
i18n/es_EC.po
i18n/es_MX.po
i18n/es_PY.po
i18n/es_VE.po
i18n/et.po
i18n/fi.po
i18n/fr.po
i18n/gl.po
i18n/hr.po
i18n/hu.po
i18n/it.po
i18n/ja.po
i18n/mk.po
i18n/mn.po
i18n/nb.po
i18n/nl.po
i18n/pl.po
i18n/pt.po
i18n/pt_BR.po
i18n/ro.po
i18n/ru.po
i18n/sk.po
i18n/sl.po
i18n/sr.po
i18n/sr@latin.po
i18n/sv.po
i18n/tr.po
i18n/vi.po
i18n/zh_CN.po
i18n/zh_TW.po
images/1_configure_ftp.jpeg
images/2_document_browse.jpeg
images/3_document_ftp.jpeg
openerp_document_ftp.egg-info/PKG-INFO
openerp_document_ftp.egg-info/SOURCES.txt
openerp_document_ftp.egg-info/dependency_links.txt
openerp_document_ftp.egg-info/requires.txt
openerp_document_ftp.egg-info/top_level.txt
security/ir.model.access.csv
test/document_ftp_test.yml
test/document_ftp_test2.yml
test/document_ftp_test3.yml
test/document_ftp_test4.yml
test/document_ftp_test5.yml
wizard/ftp_browse_view.xml
wizard/ftp_configuration_view.xml